{
  "display": {
    "icon": {
      "item": "pokecube:pokecube"
    },
    "title": {
      "translate": "achievement.pokecube.kill",
      "with": [
        {
          "translate": "pkmn.Phanpy.name"
        }
      ]
    },
    "description": {
      "translate": "achievement.pokecube.kill.desc",
      "with": [
        {
          "translate": "pkmn.Phanpy.name"
        }
      ]
    }
  },
  "criteria": {
    "kill_Phanpy": {
      "trigger": "pokecube:kill",
      "conditions": {
        "entry": "Phanpy"
      }
    }
  },
  "parent": "pokecube:kill/root",
  "entry": "Phanpy"
}